runmetrics/__init__.py
runmetrics/stats_collector.py
netflix_spectator_py_runtime_metrics-1.0.4.dist-info/LICENSE
netflix_spectator_py_runtime_metrics-1.0.4.dist-info/METADATA
netflix_spectator_py_runtime_metrics-1.0.4.dist-info/WHEEL
netflix_spectator_py_runtime_metrics-1.0.4.dist-info/top_level.txt
netflix_spectator_py_runtime_metrics-1.0.4.dist-info/RECORD
