Metadata-Version: 2.1
Name: netflix-spectator-py-runtime-metrics
Version: 1.0.4
Summary: Library to collect runtime metrics for Python applications using spectator-py.
Home-page: https://github.com/Netflix/spectator-py-runtime-metrics
Author: Netflix Telemetry Engineering
Author-email: netflix-atlas@googlegroups.com
License: Apache 2.0
Requires-Python: >3.8
License-File: LICENSE
Requires-Dist: netflix-spectator-py >=1.0.0
Provides-Extra: dev
Requires-Dist: check-manifest ; extra == 'dev'
Requires-Dist: pylint ; extra == 'dev'
Requires-Dist: pytest-cov ; extra == 'dev'
Requires-Dist: pytest ; extra == 'dev'
